{"cameraMode":{"drawMode":0,"name":"Shaded","section":"Shading Mode"},"sceneLighting":true,"audioPlay":false,"sceneViewState":{"showFog":true,"showMaterialUpdate":false,"showSkybox":true,"showFlares":true,"showImageEffects":true,"showParticleSystems":true,"showVisualEffectGraphs":true,"m_FxEnabled":false},"in2DMode":false,"pivot":{"x":-4.983194351196289,"y":6.860064506530762,"z":11.039335250854493},"rotation":{"x":-0.19980721175670625,"y":0.170100599527359,"z":-0.035243649035692218,"w":-0.964316189289093},"size":26.627975463867189,"orthographic":false}